rmsp/__init__.py
rmsp/interactorhelper.py
rmsp/mphelper.py
rmsp/rmsbuilder.py
rmsp/rmscore.py
rmsp/rmsinteractor.py
rmsp/rmstemplate.py
rmsp/rmstools.py
rmsp/rmsutils.py
rmsp/example/__init__.py
rmsp/example/example1.py
rmsp-0.1.0.dist-info/METADATA
rmsp-0.1.0.dist-info/WHEEL
rmsp-0.1.0.dist-info/entry_points.txt
rmsp-0.1.0.dist-info/top_level.txt
rmsp-0.1.0.dist-info/RECORD
