Metadata-Version: 2.1
Name: rmsp
Version: 0.1.0
Summary: Resource management system for python
Home-page: https://github.com/aldenleung/rmsp/
Author: Alden Leung
Author-email: alden.leung@gmail.com
Classifier: Programming Language :: Python :: 3.7
Classifier: Programming Language :: Python :: 3.8
Classifier: Programming Language :: Python :: 3.9
Classifier: License :: OSI Approved :: GNU General Public License v3 (GPLv3)
Requires-Dist: python-dateutil (>=2.8.2)
Requires-Dist: dill (>=0.3.5.1)
Requires-Dist: networkx (>=2.8.0)
Requires-Dist: psutil (>=5.9.5)
Requires-Dist: requests (>=2.29.0)
Requires-Dist: commonhelper (>=0.0.5)
Requires-Dist: mphelper (>=0.0.3)
Requires-Dist: biodata (>=0.1.0)
Requires-Dist: simplevc (>=0.0.3)
